{
    "kind": "youtube#channelListResponse",
    "etag": "kTt-RKB7glq47C9j8f4Z91G4wJA",
    "pageInfo": {
        "totalResults": 1,
        "resultsPerPage": 5
    },
    "items": [
        {
            "kind": "youtube#channel",
            "etag": "DeQMlGEXdBKa0Z0pcbTfuNyhyCo",
            "id": "UCovAQCyXar8ra_WC2bLGqIA",
            "statistics": {
                "viewCount": "832527",
                "subscriberCount": "710",
                "hiddenSubscriberCount": false,
                "videoCount": "1963"
            }
        }
    ]
}